{
    "date": "2023-11-28 12:31:14",
    "algorithm": "LinearSVC",
    "dataset": "breast_cancer",
    "labeled_size": 0.3,
    "hyperparameters": "{'max_iter': 10000}",
    "results_train": {
        "train_accuracy": 0.9926470588235294,
        "train_precision": 0.9883720930232558,
        "train_recall": 1.0,
        "train_f1_score": 0.9941520467836257
    },
    "results_test": {
        "test_accuracy": 0.9824561403508771,
        "test_precision": 0.9859154929577465,
        "test_recall": 0.9859154929577465,
        "test_f1_score": 0.9859154929577465,
        "training_time": 0.001331329345703125
    }
}{
    "date": "2023-11-28 12:31:14",
    "algorithm": "LinearSVC",
    "dataset": "breast_cancer",
    "labeled_size": 0.5,
    "hyperparameters": "{'max_iter': 10000}",
    "results_train": {
        "train_accuracy": 0.9911894273127754,
        "train_precision": 0.9862068965517241,
        "train_recall": 1.0,
        "train_f1_score": 0.9930555555555556
    },
    "results_test": {
        "test_accuracy": 0.956140350877193,
        "test_precision": 0.9714285714285714,
        "test_recall": 0.9577464788732394,
        "test_f1_score": 0.9645390070921985,
        "training_time": 0.002166271209716797
    }
}{
    "date": "2023-11-28 12:31:14",
    "algorithm": "LinearSVC",
    "dataset": "breast_cancer",
    "labeled_size": 0.7,
    "hyperparameters": "{'max_iter': 10000}",
    "results_train": {
        "train_accuracy": 0.9905660377358491,
        "train_precision": 0.9900497512437811,
        "train_recall": 0.995,
        "train_f1_score": 0.9925187032418954
    },
    "results_test": {
        "test_accuracy": 0.9473684210526315,
        "test_precision": 0.9577464788732394,
        "test_recall": 0.9577464788732394,
        "test_f1_score": 0.9577464788732394,
        "training_time": 0.002134084701538086
    }
}{
    "date": "2023-11-28 12:31:14",
    "algorithm": "LinearSVC",
    "dataset": "breast_cancer",
    "labeled_size": 0.9,
    "hyperparameters": "{'max_iter': 10000}",
    "results_train": {
        "train_accuracy": 0.9877750611246944,
        "train_precision": 0.9846153846153847,
        "train_recall": 0.9961089494163424,
        "train_f1_score": 0.9903288201160542
    },
    "results_test": {
        "test_accuracy": 0.9649122807017544,
        "test_precision": 0.9855072463768116,
        "test_recall": 0.9577464788732394,
        "test_f1_score": 0.9714285714285714,
        "training_time": 0.009302854537963867
    }
}{
    "date": "2023-11-28 12:31:14",
    "algorithm": "LinearSVC",
    "dataset": "breast_cancer",
    "labeled_size": 1.0,
    "hyperparameters": "{'max_iter': 10000}",
    "results_train": {
        "train_accuracy": 0.9868131868131869,
        "train_precision": 0.9861111111111112,
        "train_recall": 0.993006993006993,
        "train_f1_score": 0.9895470383275262
    },
    "results_test": {
        "test_accuracy": 0.956140350877193,
        "test_precision": 0.9714285714285714,
        "test_recall": 0.9577464788732394,
        "test_f1_score": 0.9645390070921985,
        "training_time": 0.008652687072753906
    }
}