{
    "date": "2023-11-22 13:58:43",
    "algorithm": "Assemble",
    "dataset": "imdb",
    "labeled_size": 0.3,
    "hyperparameters": "{'base_estimator': RandomForestClassifier(), 'T': 3}",
    "results_train": {
        "train_accuracy": 1.0,
        "train_precision": 1.0,
        "train_recall": 1.0,
        "train_f1_score": 1.0
    },
    "results_test": {
        "test_accuracy": 0.80168,
        "test_precision": 0.7941956623498205,
        "test_recall": 0.8144,
        "test_f1_score": 0.8041709455723202,
        "training_time": 69.48402547836304
    }
}{
    "date": "2023-11-22 14:02:30",
    "algorithm": "Assemble",
    "dataset": "imdb",
    "labeled_size": 0.3,
    "hyperparameters": "{'base_estimator': RandomForestClassifier(), 'T': 10}",
    "results_train": {
        "train_accuracy": 1.0,
        "train_precision": 1.0,
        "train_recall": 1.0,
        "train_f1_score": 1.0
    },
    "results_test": {
        "test_accuracy": 0.80436,
        "test_precision": 0.7975752835353931,
        "test_recall": 0.81576,
        "test_f1_score": 0.8065651572078308,
        "training_time": 205.20206451416016
    }
}{
    "date": "2023-11-22 14:44:52",
    "algorithm": "Assemble",
    "dataset": "imdb",
    "labeled_size": 0.3,
    "hyperparameters": "{'base_estimator': RandomForestClassifier(), 'T': 50}",
    "results_train": {
        "train_accuracy": 1.0,
        "train_precision": 1.0,
        "train_recall": 1.0,
        "train_f1_score": 1.0
    },
    "results_test": {
        "test_accuracy": 0.80232,
        "test_precision": 0.7931275209432206,
        "test_recall": 0.818,
        "test_f1_score": 0.8053717706364208,
        "training_time": 2433.069043159485
    }
}{
    "date": "2023-11-22 17:07:06",
    "algorithm": "Assemble",
    "dataset": "imdb",
    "labeled_size": 0.3,
    "hyperparameters": "{'base_estimator': RandomForestClassifier(), 'T': 100}",
    "results_train": {
        "train_accuracy": 0.9964,
        "train_precision": 0.9938975855664632,
        "train_recall": 0.9989333333333333,
        "train_f1_score": 0.9964090969543823
    },
    "results_test": {
        "test_accuracy": 0.78876,
        "test_precision": 0.7821464863597279,
        "test_recall": 0.80048,
        "test_f1_score": 0.7912070533349147,
        "training_time": 8328.83552145958
    }
}{
    "date": "2023-11-22 22:04:21",
    "algorithm": "Assemble",
    "dataset": "imdb",
    "labeled_size": 0.3,
    "hyperparameters": "{'base_estimator': RandomForestClassifier(), 'T': 150}",
    "results_train": {
        "train_accuracy": 0.9857333333333334,
        "train_precision": 0.9797208322359757,
        "train_recall": 0.992,
        "train_f1_score": 0.9858221809990725
    },
    "results_test": {
        "test_accuracy": 0.78388,
        "test_precision": 0.7772915527076658,
        "test_recall": 0.79576,
        "test_f1_score": 0.7864173617424992,
        "training_time": 17536.935671567917
    }
}{
    "date": "2023-11-23 16:21:00",
    "algorithm": "Assemble",
    "dataset": "imdb",
    "labeled_size": 0.3,
    "hyperparameters": "{'base_estimator': RandomForestClassifier(), 'T': 300}",
    "results_train": {
        "train_accuracy": 0.9692,
        "train_precision": 0.9585613760750586,
        "train_recall": 0.9808,
        "train_f1_score": 0.9695531830763148
    },
    "results_test": {
        "test_accuracy": 0.7796,
        "test_precision": 0.7748938178386031,
        "test_recall": 0.78816,
        "test_f1_score": 0.7814706115650035,
        "training_time": 65221.7084505558
    }
}{
    "date": "2023-11-23 16:21:38",
    "algorithm": "Assemble",
    "dataset": "imdb",
    "labeled_size": 0.3,
    "hyperparameters": "{'base_estimator': DecisionTreeClassifier(), 'T': 3}",
    "results_train": {
        "train_accuracy": 1.0,
        "train_precision": 1.0,
        "train_recall": 1.0,
        "train_f1_score": 1.0
    },
    "results_test": {
        "test_accuracy": 0.62124,
        "test_precision": 0.6201919264017766,
        "test_recall": 0.6256,
        "test_f1_score": 0.6228842247799594,
        "training_time": 37.40688157081604
    }
}{
    "date": "2023-11-23 16:22:42",
    "algorithm": "Assemble",
    "dataset": "imdb",
    "labeled_size": 0.3,
    "hyperparameters": "{'base_estimator': DecisionTreeClassifier(), 'T': 10}",
    "results_train": {
        "train_accuracy": 1.0,
        "train_precision": 1.0,
        "train_recall": 1.0,
        "train_f1_score": 1.0
    },
    "results_test": {
        "test_accuracy": 0.6202,
        "test_precision": 0.6194641011369961,
        "test_recall": 0.62328,
        "test_f1_score": 0.621366192128245,
        "training_time": 62.755528926849365
    }
}{
    "date": "2023-11-23 16:27:34",
    "algorithm": "Assemble",
    "dataset": "imdb",
    "labeled_size": 0.3,
    "hyperparameters": "{'base_estimator': DecisionTreeClassifier(), 'T': 50}",
    "results_train": {
        "train_accuracy": 1.0,
        "train_precision": 1.0,
        "train_recall": 1.0,
        "train_f1_score": 1.0
    },
    "results_test": {
        "test_accuracy": 0.71252,
        "test_precision": 0.709189699976376,
        "test_recall": 0.72048,
        "test_f1_score": 0.714790269455137,
        "training_time": 285.92844820022583
    }
}{
    "date": "2023-11-23 16:39:22",
    "algorithm": "Assemble",
    "dataset": "imdb",
    "labeled_size": 0.3,
    "hyperparameters": "{'base_estimator': DecisionTreeClassifier(), 'T': 100}",
    "results_train": {
        "train_accuracy": 0.9997333333333334,
        "train_precision": 0.9997333333333334,
        "train_recall": 0.9997333333333334,
        "train_f1_score": 0.9997333333333334
    },
    "results_test": {
        "test_accuracy": 0.74944,
        "test_precision": 0.7410327767470625,
        "test_recall": 0.76688,
        "test_f1_score": 0.7537348639723228,
        "training_time": 697.098340511322
    }
}{
    "date": "2023-11-23 17:01:12",
    "algorithm": "Assemble",
    "dataset": "imdb",
    "labeled_size": 0.3,
    "hyperparameters": "{'base_estimator': DecisionTreeClassifier(), 'T': 150}",
    "results_train": {
        "train_accuracy": 0.9966666666666667,
        "train_precision": 0.9973297730307076,
        "train_recall": 0.996,
        "train_f1_score": 0.9966644429619747
    },
    "results_test": {
        "test_accuracy": 0.75408,
        "test_precision": 0.7446841294298921,
        "test_recall": 0.77328,
        "test_f1_score": 0.7587127158555729,
        "training_time": 1292.8367121219635
    }
}{
    "date": "2023-11-23 18:11:21",
    "algorithm": "Assemble",
    "dataset": "imdb",
    "labeled_size": 0.3,
    "hyperparameters": "{'base_estimator': DecisionTreeClassifier(), 'T': 300}",
    "results_train": {
        "train_accuracy": 0.9824,
        "train_precision": 0.981629392971246,
        "train_recall": 0.9832,
        "train_f1_score": 0.9824140687450039
    },
    "results_test": {
        "test_accuracy": 0.75364,
        "test_precision": 0.7410476697331407,
        "test_recall": 0.77976,
        "test_f1_score": 0.7599111215062566,
        "training_time": 4175.248146057129
    }
}{
    "date": "2023-11-23 18:11:38",
    "algorithm": "Assemble",
    "dataset": "imdb",
    "labeled_size": 0.3,
    "hyperparameters": "{'base_estimator': GaussianNB(), 'T': 3}",
    "results_train": {
        "train_accuracy": 0.8057333333333333,
        "train_precision": 0.7994254374510316,
        "train_recall": 0.8162666666666667,
        "train_f1_score": 0.8077582794563927
    },
    "results_test": {
        "test_accuracy": 0.78416,
        "test_precision": 0.7869143780290792,
        "test_recall": 0.77936,
        "test_f1_score": 0.7831189710610934,
        "training_time": 5.037669897079468
    }
}{
    "date": "2023-11-23 18:12:18",
    "algorithm": "Assemble",
    "dataset": "imdb",
    "labeled_size": 0.3,
    "hyperparameters": "{'base_estimator': GaussianNB(), 'T': 10}",
    "results_train": {
        "train_accuracy": 0.8316,
        "train_precision": 0.8239124772076062,
        "train_recall": 0.8434666666666667,
        "train_f1_score": 0.8335749110554751
    },
    "results_test": {
        "test_accuracy": 0.7882,
        "test_precision": 0.7890556045895851,
        "test_recall": 0.78672,
        "test_f1_score": 0.7878860713856507,
        "training_time": 32.226983308792114
    }
}{
    "date": "2023-11-23 18:23:36",
    "algorithm": "Assemble",
    "dataset": "imdb",
    "labeled_size": 0.3,
    "hyperparameters": "{'base_estimator': GaussianNB(), 'T': 50}",
    "results_train": {
        "train_accuracy": 0.8556,
        "train_precision": 0.8504599211563731,
        "train_recall": 0.8629333333333333,
        "train_f1_score": 0.8566512243547318
    },
    "results_test": {
        "test_accuracy": 0.79084,
        "test_precision": 0.7953050117780847,
        "test_recall": 0.78328,
        "test_f1_score": 0.789246705090484,
        "training_time": 639.3140022754669
    }
}{
    "date": "2023-11-23 19:06:16",
    "algorithm": "Assemble",
    "dataset": "imdb",
    "labeled_size": 0.3,
    "hyperparameters": "{'base_estimator': GaussianNB(), 'T': 100}",
    "results_train": {
        "train_accuracy": 0.8201333333333334,
        "train_precision": 0.8140204028250065,
        "train_recall": 0.8298666666666666,
        "train_f1_score": 0.8218671596461111
    },
    "results_test": {
        "test_accuracy": 0.78632,
        "test_precision": 0.7907392363931762,
        "test_recall": 0.77872,
        "test_f1_score": 0.7846835953244659,
        "training_time": 2483.892853975296
    }
}{
    "date": "2023-11-23 20:40:27",
    "algorithm": "Assemble",
    "dataset": "imdb",
    "labeled_size": 0.3,
    "hyperparameters": "{'base_estimator': GaussianNB(), 'T': 150}",
    "results_train": {
        "train_accuracy": 0.7985333333333333,
        "train_precision": 0.7968708565367276,
        "train_recall": 0.8013333333333333,
        "train_f1_score": 0.7990958649115809
    },
    "results_test": {
        "test_accuracy": 0.7808,
        "test_precision": 0.7864370817692182,
        "test_recall": 0.77096,
        "test_f1_score": 0.7786216369071666,
        "training_time": 5534.960125923157
    }
}{
    "date": "2023-11-24 02:49:30",
    "algorithm": "Assemble",
    "dataset": "imdb",
    "labeled_size": 0.3,
    "hyperparameters": "{'base_estimator': GaussianNB(), 'T': 300}",
    "results_train": {
        "train_accuracy": 0.7912,
        "train_precision": 0.7908897176345232,
        "train_recall": 0.7917333333333333,
        "train_f1_score": 0.7913113006396588
    },
    "results_test": {
        "test_accuracy": 0.77696,
        "test_precision": 0.7853610286844708,
        "test_recall": 0.76224,
        "test_f1_score": 0.7736278012341669,
        "training_time": 21911.145736932755
    }
}